[{"subcat": [{"subcategory": "Alarma Auto", "quantity": 3}, {"subcategory": null, "quantity": 1}, {"subcategory": "Radio 1 din", "quantity": 1}, {"subcategory": "otros", "quantity": 0}]}, {"cig_stats": [{"cig": "", "quantity": 4}]}, {"prod_stats": [{"product": "ALARMA  Exact 360 Impacto", "quantity": 1}, {"product": "ALARMA Cyber FX 360", "quantity": 1}, {"product": "SP 2240 BT", "quantity": 1}, {"product": "Tacografo TC100", "quantity": 1}]}, {"reason_stats": [{"reason": "Botonera", "quantity": 1}, {"reason": "Da\u00f1o Electrico-Rotura", "quantity": 1}, {"reason": "Falla Bluetooth", "quantity": 1}, {"reason": "Falla Sensor Ultrasonido", "quantity": 1}]}, {"family_scrap": []}, {"family_repair": []}]